rdsclient/__init__.py
rdsclient/rds.py
rdsclient-0.1.0.dist-info/licenses/LICENSE
rdsclient-0.1.0.dist-info/METADATA
rdsclient-0.1.0.dist-info/WHEEL
rdsclient-0.1.0.dist-info/top_level.txt
rdsclient-0.1.0.dist-info/RECORD
