Metadata-Version: 2.4
Name: rdsclient
Version: 0.1.0
Summary: A Python wrapper for querying AWS RDS with mysql-connector-python, returning Pandas or Spark DataFrames.
Author: Adhi
License: MIT
Classifier: Development Status :: 3 - Alpha
Classifier: Programming Language :: Python :: 3
Classifier: License :: OSI Approved :: MIT License
Classifier: Operating System :: OS Independent
Classifier: Intended Audience :: Developers
Classifier: Topic :: Database :: Front-Ends
Requires-Python: >=3.7
License-File: LICENSE
Requires-Dist: mysql-connector-python
Requires-Dist: pandas
Requires-Dist: pyspark
Dynamic: license-file
